LICENSE.txt
MANIFEST.in
Makefile
README.first
README.md
VERSION
configure.ac
setup.py
bin/richard_parker
lib/procszoo/my_init
procszoo/__init__.py
procszoo.egg-info/PKG-INFO
procszoo.egg-info/SOURCES.txt
procszoo.egg-info/dependency_links.txt
procszoo.egg-info/top_level.txt
procszoo/c_functions/__init__.py
procszoo/c_functions/macros.py.in
procszoo/c_functions/atfork/atfork.c
procszoo/c_functions/atfork/atfork.h
procszoo/c_functions/atfork/atfork_module.c
procszoo/namespaces/__init__.py
procszoo/namespaces/exceptions.py